Mypackage_STT/__init__.py
mypackage_stt-0.1.dist-info/METADATA
mypackage_stt-0.1.dist-info/WHEEL
mypackage_stt-0.1.dist-info/top_level.txt
mypackage_stt-0.1.dist-info/RECORD
