Metadata-Version: 2.4
Name: Mypackage-STT
Version: 0.1
Summary: this is speech to text package created by budhyadeb bag
Author: Budhyadeb Bag
Author-email: budhya03@gmail.com
Dynamic: author
Dynamic: author-email
Dynamic: summary
